{"region_name":"Calabria","region_id":18,"people_data":{"people":10622,"houses":4993},"type":"city","city_id":80007,"city_id_2017":80007,"city_name":"Bagnara Calabra","province_id":80,"province_name":"Reggio di Calabria","pcn":null,"work_progress":{"fiber":{"status":"terminato","all_status":["terminato"],"dates":{"data_prevista_avvio_lavori":"2021-12-07","data_prevista_chiusura_lavori":"2021-12-28","data_prevista_operativita":"2022-02-08"}},"wireless":{"status":"in progettazione esecutiva","all_status":["in progettazione esecutiva"],"dates":{"data_prevista_avvio_lavori":"2021-06-30","data_prevista_chiusura_lavori":"2022-06-30","data_prevista_operativita":null}}},"intervento":{"fiber":"concessione","wireless":"concessione"},"all_intervento":{"wireless":{"concessione":true,"diretto":false},"fiber":{"concessione":true,"diretto":false}},"districts":null}