{"region_name":"Lazio","region_id":12,"people_data":{"people":2933,"houses":1567},"type":"city","city_id":57029,"city_id_2017":57029,"city_name":"Forano","province_id":57,"province_name":"Rieti","pcn":{"pcn_route":"POP_RI_08_TARANO","sede_name":"Tarano","sede_id":"57067","work_status":"collaudo terminato","ordine_direttrice":"","direttrice":"","cab_transitorio":true},"work_progress":{"fiber":{"status":"terminato","all_status":["terminato"],"dates":{"data_prevista_avvio_lavori":"2018-08-10","data_prevista_chiusura_lavori":"2019-09-10","data_prevista_operativita":"2020-11-02"}},"wireless":{"status":"in progettazione definitiva","all_status":["in progettazione definitiva"],"dates":{"data_prevista_avvio_lavori":"2021-06-30","data_prevista_chiusura_lavori":"2022-06-30","data_prevista_operativita":null}}},"intervento":{"fiber":"concessione","wireless":"concessione"},"all_intervento":{"wireless":{"concessione":true,"diretto":false},"fiber":{"concessione":true,"diretto":false}},"districts":null}