{"region_name":"Friuli Venezia Giulia","region_id":6,"people_data":{"people":2911,"houses":1717},"type":"city","city_id":30019,"city_id_2017":30019,"city_name":"Cassacco","province_id":30,"province_name":"Udine","pcn":{"pcn_route":"POP_UD_04_MAJANO","sede_name":"Majano","sede_id":"30053","work_status":"collaudo terminato","ordine_direttrice":"3","direttrice":"D2","cab_transitorio":false},"work_progress":{"fiber":{"status":"terminato","all_status":["terminato"],"dates":{"data_prevista_avvio_lavori":"2019-08-20","data_prevista_chiusura_lavori":"2020-10-30","data_prevista_operativita":"2021-01-29"}},"wireless":{"status":"in progettazione definitiva","all_status":["in progettazione definitiva"],"dates":{"data_prevista_avvio_lavori":"2021-06-30","data_prevista_chiusura_lavori":"2022-06-30","data_prevista_operativita":null}}},"intervento":{"fiber":"concessione","wireless":"concessione"},"all_intervento":{"wireless":{"concessione":true,"diretto":false},"fiber":{"concessione":true,"diretto":false}},"districts":null}