{"region_name":"Piemonte","region_id":1,"people_data":{"people":712,"houses":582},"type":"city","city_id":6112,"city_id_2017":6112,"city_name":"Morsasco","province_id":6,"province_name":"Alessandria","pcn":{"pcn_route":"POP_AL_40_VISONE","sede_name":"Visone","sede_id":"6187","work_status":"in progettazione esecutiva","ordine_direttrice":"","direttrice":"","cab_transitorio":false},"work_progress":{"fiber":{"status":"terminato","all_status":["terminato"],"dates":{"data_prevista_avvio_lavori":"2020-07-20","data_prevista_chiusura_lavori":"2022-02-28","data_prevista_operativita":"2022-11-24"}},"wireless":{"status":"in programmazione","all_status":["in programmazione"],"dates":{"data_prevista_avvio_lavori":"2022-06-30","data_prevista_chiusura_lavori":"2022-12-31","data_prevista_operativita":null}}},"intervento":{"fiber":"concessione","wireless":"concessione"},"all_intervento":{"wireless":{"concessione":true,"diretto":false},"fiber":{"concessione":true,"diretto":false}},"districts":null}