{"region_name":"Lazio","region_id":12,"people_data":{"people":1741,"houses":1599},"type":"city","city_id":56013,"city_id_2017":56013,"city_name":"Capodimonte","province_id":56,"province_name":"Viterbo","pcn":{"pcn_route":"POP_VT_04_MARTA","sede_name":"Marta","sede_id":"56034","work_status":"collaudo terminato","ordine_direttrice":"1","direttrice":"D1","cab_transitorio":false},"work_progress":{"fiber":{"status":"terminato","all_status":["terminato"],"dates":{"data_prevista_avvio_lavori":"2019-08-27","data_prevista_chiusura_lavori":"2020-12-23","data_prevista_operativita":"2021-05-14"}},"wireless":{"status":"in progettazione definitiva","all_status":["in progettazione definitiva"],"dates":{"data_prevista_avvio_lavori":"2021-06-30","data_prevista_chiusura_lavori":"2022-06-30","data_prevista_operativita":null}}},"intervento":{"fiber":"concessione","wireless":"concessione"},"all_intervento":{"wireless":{"concessione":true,"diretto":false},"fiber":{"concessione":true,"diretto":false}},"districts":null}