{"region_name":"Veneto","region_id":5,"people_data":{"people":8810,"houses":4682},"type":"city","city_id":24074,"city_id_2017":24074,"city_name":"Noventa Vicentina","province_id":24,"province_name":"Vicenza","pcn":{"pcn_route":"POP_VI_49_CAMPIGLIA_DEI_BERICI","sede_name":"Campiglia dei Berici","sede_id":"24022","work_status":"collaudo terminato","ordine_direttrice":"2","direttrice":"D1","cab_transitorio":false},"work_progress":{"fiber":{"status":"terminato","all_status":["terminato"],"dates":{"data_prevista_avvio_lavori":"2018-08-16","data_prevista_chiusura_lavori":"2019-07-31","data_prevista_operativita":"2021-03-05"}},"wireless":{"status":"terminato","all_status":["terminato"],"dates":{"data_prevista_avvio_lavori":"2019-10-30","data_prevista_chiusura_lavori":"2020-06-19","data_prevista_operativita":null}}},"intervento":{"fiber":"concessione","wireless":"concessione"},"all_intervento":{"wireless":{"concessione":true,"diretto":false},"fiber":{"concessione":true,"diretto":false}},"districts":null}