{"region_name":"Campania","region_id":15,"people_data":{"people":5766810,"houses":2838925,"cities":550},"type":"region","work_progress":{"mean_status":{"fiber":70.37861915367483,"wireless":19.39163498098859},"diretto":{"fiber":{"status":{"in programmazione":0,"in progettazione definitiva":0,"in progettazione esecutiva":0,"in esecuzione":0,"lavori chiusi":0,"in collaudo":0,"terminato":0},"2018":{"in programmazione":0,"in progettazione definitiva":0,"in progettazione esecutiva":0,"in esecuzione":0,"lavori chiusi":0,"in collaudo":0,"terminato":0},"2019":{"in programmazione":0,"in progettazione definitiva":0,"in progettazione esecutiva":0,"in esecuzione":0,"lavori chiusi":0,"in collaudo":0,"terminato":0},"2020":{"in programmazione":0,"in progettazione definitiva":0,"in progettazione esecutiva":0,"in esecuzione":0,"lavori chiusi":0,"in collaudo":0,"terminato":0},"2021":{"in programmazione":0,"in progettazione definitiva":0,"in progettazione esecutiva":0,"in esecuzione":0,"lavori chiusi":0,"in collaudo":0,"terminato":0},"2022":{"in programmazione":0,"in progettazione definitiva":0,"in progettazione esecutiva":0,"in esecuzione":0,"lavori chiusi":0,"in collaudo":0,"terminato":0}},"wireless":{"status":{"in programmazione":0,"in progettazione definitiva":0,"in progettazione esecutiva":0,"in esecuzione":0,"lavori chiusi":0,"in collaudo":0,"terminato":0},"2018":{"in programmazione":0,"in progettazione definitiva":0,"in progettazione esecutiva":0,"in esecuzione":0,"lavori chiusi":0,"in collaudo":0,"terminato":0},"2019":{"in programmazione":0,"in progettazione definitiva":0,"in progettazione esecutiva":0,"in esecuzione":0,"lavori chiusi":0,"in collaudo":0,"terminato":0},"2020":{"in programmazione":0,"in progettazione definitiva":0,"in progettazione esecutiva":0,"in esecuzione":0,"lavori chiusi":0,"in collaudo":0,"terminato":0},"2021":{"in programmazione":0,"in progettazione definitiva":0,"in progettazione esecutiva":0,"in esecuzione":0,"lavori chiusi":0,"in collaudo":0,"terminato":0},"2022":{"in programmazione":0,"in progettazione definitiva":0,"in progettazione esecutiva":0,"in esecuzione":0,"lavori chiusi":0,"in collaudo":0,"terminato":0}}},"concessione":{"fiber":{"status":{"in programmazione":97,"in progettazione definitiva":1,"in progettazione esecutiva":76,"in esecuzione":31,"lavori chiusi":9,"in collaudo":16,"terminato":316},"2018":{"in programmazione":97,"in progettazione definitiva":108,"in progettazione esecutiva":9,"in esecuzione":16,"lavori chiusi":316,"in collaudo":0,"terminato":0},"2019":{"in programmazione":97,"in progettazione definitiva":77,"in progettazione esecutiva":31,"in esecuzione":9,"lavori chiusi":16,"in collaudo":316,"terminato":0},"2020":{"in programmazione":97,"in progettazione definitiva":1,"in progettazione esecutiva":76,"in esecuzione":31,"lavori chiusi":9,"in collaudo":16,"terminato":316},"2021":{"in programmazione":97,"in progettazione definitiva":0,"in progettazione esecutiva":0,"in esecuzione":77,"lavori chiusi":0,"in collaudo":40,"terminato":332},"2022":{"in programmazione":97,"in progettazione definitiva":0,"in progettazione esecutiva":0,"in esecuzione":0,"lavori chiusi":0,"in collaudo":77,"terminato":372}},"wireless":{"status":{"in programmazione":20,"in progettazione definitiva":283,"in progettazione esecutiva":89,"in esecuzione":15,"lavori chiusi":27,"in collaudo":10,"terminato":102},"2018":{"in programmazione":20,"in progettazione definitiva":387,"in progettazione esecutiva":27,"in esecuzione":10,"lavori chiusi":102,"in collaudo":0,"terminato":0},"2019":{"in programmazione":20,"in progettazione definitiva":372,"in progettazione esecutiva":15,"in esecuzione":27,"lavori chiusi":10,"in collaudo":102,"terminato":0},"2020":{"in programmazione":20,"in progettazione definitiva":283,"in progettazione esecutiva":89,"in esecuzione":15,"lavori chiusi":27,"in collaudo":10,"terminato":102},"2021":{"in programmazione":20,"in progettazione definitiva":0,"in progettazione esecutiva":0,"in esecuzione":372,"lavori chiusi":0,"in collaudo":42,"terminato":112},"2022":{"in programmazione":20,"in progettazione definitiva":0,"in progettazione esecutiva":0,"in esecuzione":0,"lavori chiusi":0,"in collaudo":372,"terminato":154}}}},"no_infratel_cities":4,"intervento":{"diretto":{"fiber":0,"wireless":0},"concessione":{"fiber":546,"wireless":546}},"cantieri":{"diretto":0,"concessione":1786}}