{"region_name":"Piemonte","region_id":1,"people_data":{"people":4707,"houses":3442},"type":"city","city_id":6081,"city_id_2017":6081,"city_name":"Gavi","province_id":6,"province_name":"Alessandria","pcn":{"pcn_route":"POP_AL_05_BOSIO","sede_name":"Bosio","sede_id":"6022","work_status":"collaudo terminato","ordine_direttrice":"1","direttrice":"D3","cab_transitorio":false},"work_progress":{"fiber":{"status":"in esecuzione","all_status":["in esecuzione"],"dates":{"data_prevista_avvio_lavori":"2022-12-31","data_prevista_chiusura_lavori":"2022-12-31","data_prevista_operativita":"2022-12-31"}},"wireless":{"status":"in progettazione definitiva","all_status":["in progettazione definitiva"],"dates":{"data_prevista_avvio_lavori":"2021-12-31","data_prevista_chiusura_lavori":"2022-12-31","data_prevista_operativita":null}}},"intervento":{"fiber":"concessione","wireless":"concessione"},"all_intervento":{"wireless":{"concessione":true,"diretto":false},"fiber":{"concessione":true,"diretto":false}},"districts":null}