{"region_name":"Abruzzo","region_id":13,"people_data":{"people":590,"houses":521},"type":"city","city_id":66094,"city_id_2017":66094,"city_name":"Scontrone","province_id":66,"province_name":"L'Aquila","pcn":{"pcn_route":"POP_AQ_14_ALFEDENA","sede_name":"Alfedena","sede_id":"66003","work_status":"in progettazione esecutiva","ordine_direttrice":"1","direttrice":"D1","cab_transitorio":false},"work_progress":{"fiber":{"status":"terminato","all_status":["terminato"],"dates":{"data_prevista_avvio_lavori":"2019-09-25","data_prevista_chiusura_lavori":"2021-11-30","data_prevista_operativita":"2022-02-23"}},"wireless":{"status":"terminato","all_status":["terminato"],"dates":{"data_prevista_avvio_lavori":"2020-06-03","data_prevista_chiusura_lavori":"2020-08-26","data_prevista_operativita":null}}},"intervento":{"fiber":"concessione","wireless":"concessione"},"all_intervento":{"wireless":{"concessione":true,"diretto":false},"fiber":{"concessione":true,"diretto":false}},"districts":null}