{"region_name":"Sardegna","region_id":20,"people_data":{"people":1591,"houses":879},"type":"city","city_id":95027,"city_id_2017":95027,"city_name":"Milis","province_id":95,"province_name":"Oristano","pcn":null,"work_progress":{"fiber":{"status":"terminato","all_status":["terminato"],"dates":{"data_prevista_avvio_lavori":"2021-06-22","data_prevista_chiusura_lavori":"2021-07-23","data_prevista_operativita":"2021-08-05"}},"wireless":{"status":"terminato","all_status":["terminato"],"dates":{"data_prevista_avvio_lavori":"2022-06-24","data_prevista_chiusura_lavori":"2022-07-14","data_prevista_operativita":null}}},"intervento":{"fiber":"concessione","wireless":"concessione"},"all_intervento":{"wireless":{"concessione":true,"diretto":false},"fiber":{"concessione":true,"diretto":true}},"districts":null}