{"region_name":"Piemonte","region_id":1,"people_data":{"people":2121,"houses":1291},"type":"city","city_id":5059,"city_id_2017":5059,"city_name":"Isola d'Asti","province_id":5,"province_name":"Asti","pcn":{"pcn_route":"POP_AT_05_COSTIGLIOLE_D'ASTI","sede_name":"Costigliole d'Asti","sede_id":"5050","work_status":"in esecuzione","ordine_direttrice":"1","direttrice":"D1","cab_transitorio":false},"work_progress":{"fiber":{"status":"in esecuzione","all_status":["in esecuzione"],"dates":{"data_prevista_avvio_lavori":"2022-12-02","data_prevista_chiusura_lavori":"2022-12-31","data_prevista_operativita":"2022-12-31"}},"wireless":{"status":"in progettazione definitiva","all_status":["in progettazione definitiva"],"dates":{"data_prevista_avvio_lavori":"2021-12-31","data_prevista_chiusura_lavori":"2022-12-31","data_prevista_operativita":null}}},"intervento":{"fiber":"concessione","wireless":"concessione"},"all_intervento":{"wireless":{"concessione":true,"diretto":false},"fiber":{"concessione":true,"diretto":false}},"districts":null}