{"region_name":"Lombardia","region_id":3,"people_data":{"people":5207,"houses":2813},"type":"city","city_id":12139,"city_id_2017":12139,"city_name":"Viggi\u00f9","province_id":12,"province_name":"Varese","pcn":null,"work_progress":{"fiber":{"status":"in programmazione","all_status":["in programmazione"],"dates":{"data_prevista_avvio_lavori":"2022-06-30","data_prevista_chiusura_lavori":"2022-12-31","data_prevista_operativita":"2022-12-31"}},"wireless":{"status":"in progettazione esecutiva","all_status":["in progettazione esecutiva"],"dates":{"data_prevista_avvio_lavori":"2021-12-31","data_prevista_chiusura_lavori":"2022-12-31","data_prevista_operativita":null}}},"intervento":{"fiber":"concessione","wireless":"concessione"},"all_intervento":{"wireless":{"concessione":true,"diretto":false},"fiber":{"concessione":true,"diretto":false}},"districts":null}