{"region_name":"Emilia Romagna","region_id":8,"people_data":{"people":4342135,"houses":2797571,"cities":340},"type":"region","work_progress":{"mean_status":{"fiber":50.82644628099174,"wireless":19.879518072289155},"diretto":{"fiber":{"status":{"in programmazione":0,"in progettazione definitiva":0,"in progettazione esecutiva":0,"in esecuzione":0,"lavori chiusi":0,"in collaudo":0,"terminato":0},"2018":{"in programmazione":0,"in progettazione definitiva":0,"in progettazione esecutiva":0,"in esecuzione":0,"lavori chiusi":0,"in collaudo":0,"terminato":0},"2019":{"in programmazione":0,"in progettazione definitiva":0,"in progettazione esecutiva":0,"in esecuzione":0,"lavori chiusi":0,"in collaudo":0,"terminato":0},"2020":{"in programmazione":0,"in progettazione definitiva":0,"in progettazione esecutiva":0,"in esecuzione":0,"lavori chiusi":0,"in collaudo":0,"terminato":0},"2021":{"in programmazione":0,"in progettazione definitiva":0,"in progettazione esecutiva":0,"in esecuzione":0,"lavori chiusi":0,"in collaudo":0,"terminato":0},"2022":{"in programmazione":0,"in progettazione definitiva":0,"in progettazione esecutiva":0,"in esecuzione":0,"lavori chiusi":0,"in collaudo":0,"terminato":0}},"wireless":{"status":{"in programmazione":0,"in progettazione definitiva":0,"in progettazione esecutiva":0,"in esecuzione":0,"lavori chiusi":0,"in collaudo":0,"terminato":0},"2018":{"in programmazione":0,"in progettazione definitiva":0,"in progettazione esecutiva":0,"in esecuzione":0,"lavori chiusi":0,"in collaudo":0,"terminato":0},"2019":{"in programmazione":0,"in progettazione definitiva":0,"in progettazione esecutiva":0,"in esecuzione":0,"lavori chiusi":0,"in collaudo":0,"terminato":0},"2020":{"in programmazione":0,"in progettazione definitiva":0,"in progettazione esecutiva":0,"in esecuzione":0,"lavori chiusi":0,"in collaudo":0,"terminato":0},"2021":{"in programmazione":0,"in progettazione definitiva":0,"in progettazione esecutiva":0,"in esecuzione":0,"lavori chiusi":0,"in collaudo":0,"terminato":0},"2022":{"in programmazione":0,"in progettazione definitiva":0,"in progettazione esecutiva":0,"in esecuzione":0,"lavori chiusi":0,"in collaudo":0,"terminato":0}}},"concessione":{"fiber":{"status":{"in programmazione":98,"in progettazione definitiva":0,"in progettazione esecutiva":6,"in esecuzione":39,"lavori chiusi":22,"in collaudo":52,"terminato":123},"2018":{"in programmazione":98,"in progettazione definitiva":45,"in progettazione esecutiva":22,"in esecuzione":52,"lavori chiusi":123,"in collaudo":0,"terminato":0},"2019":{"in programmazione":98,"in progettazione definitiva":6,"in progettazione esecutiva":39,"in esecuzione":22,"lavori chiusi":52,"in collaudo":123,"terminato":0},"2020":{"in programmazione":98,"in progettazione definitiva":0,"in progettazione esecutiva":6,"in esecuzione":39,"lavori chiusi":22,"in collaudo":52,"terminato":123},"2021":{"in programmazione":98,"in progettazione definitiva":0,"in progettazione esecutiva":0,"in esecuzione":6,"lavori chiusi":0,"in collaudo":61,"terminato":175},"2022":{"in programmazione":98,"in progettazione definitiva":0,"in progettazione esecutiva":0,"in esecuzione":0,"lavori chiusi":0,"in collaudo":6,"terminato":236}},"wireless":{"status":{"in programmazione":8,"in progettazione definitiva":101,"in progettazione esecutiva":88,"in esecuzione":7,"lavori chiusi":38,"in collaudo":32,"terminato":66},"2018":{"in programmazione":8,"in progettazione definitiva":196,"in progettazione esecutiva":38,"in esecuzione":32,"lavori chiusi":66,"in collaudo":0,"terminato":0},"2019":{"in programmazione":8,"in progettazione definitiva":189,"in progettazione esecutiva":7,"in esecuzione":38,"lavori chiusi":32,"in collaudo":66,"terminato":0},"2020":{"in programmazione":8,"in progettazione definitiva":101,"in progettazione esecutiva":88,"in esecuzione":7,"lavori chiusi":38,"in collaudo":32,"terminato":66},"2021":{"in programmazione":8,"in progettazione definitiva":0,"in progettazione esecutiva":0,"in esecuzione":189,"lavori chiusi":0,"in collaudo":45,"terminato":98},"2022":{"in programmazione":8,"in progettazione definitiva":0,"in progettazione esecutiva":0,"in esecuzione":0,"lavori chiusi":0,"in collaudo":189,"terminato":143}}}},"no_infratel_cities":0,"intervento":{"diretto":{"fiber":0,"wireless":0},"concessione":{"fiber":340,"wireless":340}},"cantieri":{"diretto":0,"concessione":1250}}